[
    {
        "name": "BannerRite Hellblau",
        "label": "hellblau",
        "hex": "#73cde3"
    },
    {
        "name": "BannerRite Gelb ",
        "label": "gelb",
        "hex": "#efdc56"
    },
    {
        "name": "BannerRite Rot ",
        "label": "rot",
        "hex": "#b13944"
    },
    {
        "name": "BannerRite Weiss",
        "label": "weiss",
        "hex": "#f5f5f7"
    },
    {
        "name": "BannerRite Blau ",
        "label": "blau",
        "hex": "#364d79"
    },
    {
        "name": "BannerRite Gruen",
        "label": "gruen",
        "hex": "#2ba366"
    },
    {
        "name": "BannerRite Pink fluoreszierend",
        "label": "pink-fluoreszierend",
        "hex": "#ff3ea8"
    },
    {
        "name": "BannerRite Schwarz",
        "label": "schwarz",
        "hex": "#3e3e41"
    },
    {
        "name": "BannerRite PV20 ",
        "label": "pv20",
        "hex": "#fafaf3"
    }
]